valleytext/__init__.py
valleytext/valleytext.py
valleytext-0.1.dist-info/LICENSE
valleytext-0.1.dist-info/METADATA
valleytext-0.1.dist-info/WHEEL
valleytext-0.1.dist-info/top_level.txt
valleytext-0.1.dist-info/RECORD
