Metadata-Version: 2.1
Name: valleytext
Version: 0.1
Summary: Extract keywords from sentences.
Home-page: https://github.com/yzho0907/valleytext.git
Author: young, xiuzhizheng
Author-email: 598299410@qq.com, xiuzhi_zxz@163.com
License: UNKNOWN
Platform: UNKNOWN
Classifier: Programming Language :: Python
Classifier: Programming Language :: Python :: 2.7
Classifier: Programming Language :: Python :: 3.5
Classifier: Programming Language :: Python :: 3.6
Classifier: Operating System :: OS Independent
Classifier: Intended Audience :: Developers
Classifier: License :: OSI Approved :: MIT License
